scrapeghost/__init__.py
scrapeghost/apicall.py
scrapeghost/cli.py
scrapeghost/errors.py
scrapeghost/models.py
scrapeghost/postprocessors.py
scrapeghost/preprocessors.py
scrapeghost/py.typed
scrapeghost/responses.py
scrapeghost/scrapers.py
scrapeghost/utils.py
scrapeghost-0.5.1.dist-info/LICENSE.md
scrapeghost-0.5.1.dist-info/METADATA
scrapeghost-0.5.1.dist-info/WHEEL
scrapeghost-0.5.1.dist-info/entry_points.txt
scrapeghost-0.5.1.dist-info/RECORD
