Metadata-Version: 2.1
Name: scrapeghost
Version: 0.5.1
Summary: An experimental library for scraping websites using GPT.
License: Hippocratic License HL3-EXTR-FFD-LAW-MIL-SV
Author: James Turk
Author-email: dev@jamesturk.net
Requires-Python: >=3.10,<4.0
Classifier: License :: Other/Proprietary License
Classifier: Programming Language :: Python :: 3
Classifier: Programming Language :: Python :: 3.10
Classifier: Programming Language :: Python :: 3.11
Requires-Dist: cssselect (>=1.2.0,<2.0.0)
Requires-Dist: lxml (>=4.9.2,<5.0.0)
Requires-Dist: openai (>=0.27.1,<0.28.0)
Requires-Dist: pydantic (>=1.10.7,<2.0.0)
Requires-Dist: rich (>=13.3.2,<14.0.0)
Requires-Dist: structlog (>=22.3.0,<23.0.0)
Requires-Dist: tiktoken (>=0.3.2,<0.4.0)
Requires-Dist: typer (>=0.7.0,<0.8.0)
